[
  {
    "name": "Afflicted",
    "category": "Inne",
    "description": "",
    "icon": ""
  },
  {
    "name": "Blue Scales",
    "category": "Inne",
    "description": "",
    "icon": ""
  },
  {
    "name": "Amber",
    "category": "Inne",
    "description": "",
    "icon": ""
  },
  {
    "name": "Ancient Belt",
    "category": "Inne",
    "description": "",
    "icon": ""
  },
  {
    "name": "Basalt",
    "category": "Inne",
    "description": "",
    "icon": ""
  },
  {
    "name": "Bashmu",
    "category": "Inne",
    "description": "",
    "icon": ""
  },
  {
    "name": "Blemished",
    "category": "Inne",
    "description": "",
    "icon": ""
  },
  {
    "name": "Spawn",
    "category": "Inne",
    "description": "",
    "icon": ""
  },
  {
    "name": "Bloated",
    "category": "Inne",
    "description": "",
    "icon": ""
  },
  {
    "name": "Blood",
    "category": "Inne",
    "description": "",
    "icon": ""
  },
  {
    "name": "Blood Tincture",
    "category": "Inne",
    "description": "",
    "icon": ""
  },
  {
    "name": "Bloodshot",
    "category": "Inne",
    "description": "",
    "icon": ""
  },
  {
    "name": "Blue Goanna",
    "category": "Inne",
    "description": "",
    "icon": ""
  },
  {
    "name": "Bone",
    "category": "Inne",
    "description": "",
    "icon": ""
  },
  {
    "name": "Bonecarving",
    "category": "Inne",
    "description": "",
    "icon": ""
  },
  {
    "name": "Book of",
    "category": "Inne",
    "description": "",
    "icon": ""
  },
  {
    "name": "Necromantic",
    "category": "Inne",
    "description": "",
    "icon": ""
  },
  {
    "name": "Book with a",
    "category": "Inne",
    "description": "",
    "icon": ""
  },
  {
    "name": "Book with an",
    "category": "Inne",
    "description": "",
    "icon": ""
  },
  {
    "name": "Bowl of Terror",
    "category": "Inne",
    "description": "",
    "icon": ""
  },
  {
    "name": "Brinebrute",
    "category": "Inne",
    "description": "",
    "icon": ""
  },
  {
    "name": "Broken Drak en",
    "category": "Inne",
    "description": "",
    "icon": ""
  },
  {
    "name": "Broken",
    "category": "Inne",
    "description": "",
    "icon": ""
  },
  {
    "name": "Gladiator",
    "category": "Inne",
    "description": "",
    "icon": ""
  },
  {
    "name": "Mitmah",
    "category": "Inne",
    "description": "",
    "icon": ""
  },
  {
    "name": "Broodrider",
    "category": "Inne",
    "description": "",
    "icon": ""
  },
  {
    "name": "Bulltaur Armor",
    "category": "Inne",
    "description": "",
    "icon": ""
  },
  {
    "name": "Bundle of",
    "category": "Inne",
    "description": "",
    "icon": ""
  },
  {
    "name": "Carnisylvan",
    "category": "Inne",
    "description": "",
    "icon": ""
  },
  {
    "name": "Carnivostrich",
    "category": "Inne",
    "description": "",
    "icon": ""
  },
  {
    "name": "Cave Devourer",
    "category": "Inne",
    "description": "",
    "icon": ""
  },
  {
    "name": "Chasm Spawn",
    "category": "Inne",
    "description": "",
    "icon": ""
  },
  {
    "name": "Cheesy",
    "category": "Inne",
    "description": "",
    "icon": ""
  },
  {
    "name": "Cluster of",
    "category": "Inne",
    "description": "",
    "icon": ""
  },
  {
    "name": "Crystallized",
    "category": "Inne",
    "description": "",
    "icon": ""
  },
  {
    "name": "Colourful",
    "category": "Inne",
    "description": "",
    "icon": ""
  },
  {
    "name": "Colourful Snail",
    "category": "Inne",
    "description": "",
    "icon": ""
  },
  {
    "name": "Crab Man",
    "category": "Inne",
    "description": "",
    "icon": ""
  },
  {
    "name": "Cracked",
    "category": "Inne",
    "description": "",
    "icon": ""
  },
  {
    "name": "Crawler's",
    "category": "Inne",
    "description": "",
    "icon": ""
  },
  {
    "name": "Crystal",
    "category": "Inne",
    "description": "",
    "icon": ""
  },
  {
    "name": "Crystal of the",
    "category": "Inne",
    "description": "",
    "icon": ""
  },
  {
    "name": "Crystalline",
    "category": "Inne",
    "description": "",
    "icon": ""
  },
  {
    "name": "Cursed",
    "category": "Inne",
    "description": "",
    "icon": ""
  },
  {
    "name": "Shoulder",
    "category": "Inne",
    "description": "",
    "icon": ""
  },
  {
    "name": "Damaged",
    "category": "Inne",
    "description": "",
    "icon": ""
  },
  {
    "name": "Dand elion",
    "category": "Inne",
    "description": "",
    "icon": ""
  },
  {
    "name": "Dang erous",
    "category": "Inne",
    "description": "",
    "icon": ""
  },
  {
    "name": "Dark  Obsidian",
    "category": "Inne",
    "description": "",
    "icon": ""
  },
  {
    "name": "Dark light",
    "category": "Inne",
    "description": "",
    "icon": ""
  },
  {
    "name": "Decayed",
    "category": "Inne",
    "description": "",
    "icon": ""
  },
  {
    "name": "Deepling",
    "category": "Inne",
    "description": "",
    "icon": ""
  },
  {
    "name": "Breaktime",
    "category": "Inne",
    "description": "",
    "icon": ""
  },
  {
    "name": "Guard Belt",
    "category": "Inne",
    "description": "",
    "icon": ""
  },
  {
    "name": "Deepworm",
    "category": "Inne",
    "description": "",
    "icon": ""
  },
  {
    "name": "Demonic",
    "category": "Inne",
    "description": "",
    "icon": ""
  },
  {
    "name": "Diam ond",
    "category": "Inne",
    "description": "",
    "icon": ""
  },
  {
    "name": "Diremaw",
    "category": "Inne",
    "description": "",
    "icon": ""
  },
  {
    "name": "Drag olisk",
    "category": "Inne",
    "description": "",
    "icon": ""
  },
  {
    "name": "Drag on",
    "category": "Inne",
    "description": "",
    "icon": ""
  },
  {
    "name": "Priest's",
    "category": "Inne",
    "description": "",
    "icon": ""
  },
  {
    "name": "Drak en",
    "category": "Inne",
    "description": "",
    "icon": ""
  },
  {
    "name": "Dream",
    "category": "Inne",
    "description": "",
    "icon": ""
  },
  {
    "name": "Harbinger",
    "category": "Inne",
    "description": "",
    "icon": ""
  },
  {
    "name": "Elder Bonelord",
    "category": "Inne",
    "description": "",
    "icon": ""
  },
  {
    "name": "Elven Astral",
    "category": "Inne",
    "description": "",
    "icon": ""
  },
  {
    "name": "Emerald",
    "category": "Inne",
    "description": "",
    "icon": ""
  },
  {
    "name": "Empty Honey",
    "category": "Inne",
    "description": "",
    "icon": ""
  },
  {
    "name": "GlassPojemniki na",
    "category": "Inne",
    "description": "",
    "icon": ""
  },
  {
    "name": "Encrypted",
    "category": "Inne",
    "description": "",
    "icon": ""
  },
  {
    "name": "Ensouled",
    "category": "Inne",
    "description": "",
    "icon": ""
  },
  {
    "name": "Essence of a",
    "category": "Inne",
    "description": "",
    "icon": ""
  },
  {
    "name": "Execowtioner",
    "category": "Inne",
    "description": "",
    "icon": ""
  },
  {
    "name": "Eye of a",
    "category": "Inne",
    "description": "",
    "icon": ""
  },
  {
    "name": "Eye of",
    "category": "Inne",
    "description": "",
    "icon": ""
  },
  {
    "name": "Eyeless",
    "category": "Inne",
    "description": "",
    "icon": ""
  },
  {
    "name": "Devourer",
    "category": "Inne",
    "description": "",
    "icon": ""
  },
  {
    "name": "Flask of",
    "category": "Inne",
    "description": "",
    "icon": ""
  },
  {
    "name": "Frazzle",
    "category": "Inne",
    "description": "",
    "icon": ""
  },
  {
    "name": "Frozen",
    "category": "Inne",
    "description": "",
    "icon": ""
  },
  {
    "name": "Gauze",
    "category": "Inne",
    "description": "",
    "icon": ""
  },
  {
    "name": "Ghastly",
    "category": "Inne",
    "description": "",
    "icon": ""
  },
  {
    "name": "Girlish Hair",
    "category": "Inne",
    "description": "",
    "icon": ""
  },
  {
    "name": "Girtablilu",
    "category": "Inne",
    "description": "",
    "icon": ""
  },
  {
    "name": "Warrior",
    "category": "Inne",
    "description": "",
    "icon": ""
  },
  {
    "name": "Glob of Acid",
    "category": "Inne",
    "description": "",
    "icon": ""
  },
  {
    "name": "Glooth",
    "category": "Inne",
    "description": "",
    "icon": ""
  },
  {
    "name": "Warden",
    "category": "Inne",
    "description": "",
    "icon": ""
  },
  {
    "name": "Golden Lotus",
    "category": "Inne",
    "description": "",
    "icon": ""
  },
  {
    "name": "Golden Sun",
    "category": "Inne",
    "description": "",
    "icon": ""
  },
  {
    "name": "Grappling",
    "category": "Inne",
    "description": "",
    "icon": ""
  },
  {
    "name": "Green",
    "category": "Inne",
    "description": "",
    "icon": ""
  },
  {
    "name": "Guardian",
    "category": "Inne",
    "description": "",
    "icon": ""
  },
  {
    "name": "Half-Digested",
    "category": "Inne",
    "description": "",
    "icon": ""
  },
  {
    "name": "Half-Eaten",
    "category": "Inne",
    "description": "",
    "icon": ""
  },
  {
    "name": "Harpy",
    "category": "Inne",
    "description": "",
    "icon": ""
  },
  {
    "name": "Headpecker",
    "category": "Inne",
    "description": "",
    "icon": ""
  },
  {
    "name": "Heart",
    "category": "Inne",
    "description": "",
    "icon": ""
  },
  {
    "name": "Heavy",
    "category": "Inne",
    "description": "",
    "icon": ""
  },
  {
    "name": "Hellhound",
    "category": "Inne",
    "description": "",
    "icon": ""
  },
  {
    "name": "High Guard",
    "category": "Inne",
    "description": "",
    "icon": ""
  },
  {
    "name": "Humongous",
    "category": "Inne",
    "description": "",
    "icon": ""
  },
  {
    "name": "Idol of the",
    "category": "Inne",
    "description": "",
    "icon": ""
  },
  {
    "name": "Instable Proto",
    "category": "Inne",
    "description": "",
    "icon": ""
  },
  {
    "name": "Key to the",
    "category": "Inne",
    "description": "",
    "icon": ""
  },
  {
    "name": "Drowned",
    "category": "Inne",
    "description": "",
    "icon": ""
  },
  {
    "name": "Kongra's",
    "category": "Inne",
    "description": "",
    "icon": ""
  },
  {
    "name": "Lancer Beetle",
    "category": "Inne",
    "description": "",
    "icon": ""
  },
  {
    "name": "Lavafungus",
    "category": "Inne",
    "description": "",
    "icon": ""
  },
  {
    "name": "Lavaworm",
    "category": "Inne",
    "description": "",
    "icon": ""
  },
  {
    "name": "Lightning",
    "category": "Inne",
    "description": "",
    "icon": ""
  },
  {
    "name": "Lion Cloak",
    "category": "Inne",
    "description": "",
    "icon": ""
  },
  {
    "name": "Lost Basher's",
    "category": "Inne",
    "description": "",
    "icon": ""
  },
  {
    "name": "Magma",
    "category": "Inne",
    "description": "",
    "icon": ""
  },
  {
    "name": "Makara",
    "category": "Inne",
    "description": "",
    "icon": ""
  },
  {
    "name": "Mammoth",
    "category": "Inne",
    "description": "",
    "icon": ""
  },
  {
    "name": "Mantosaurus",
    "category": "Inne",
    "description": "",
    "icon": ""
  },
  {
    "name": "Mega Drag on",
    "category": "Inne",
    "description": "",
    "icon": ""
  },
  {
    "name": "Mercenary",
    "category": "Inne",
    "description": "",
    "icon": ""
  },
  {
    "name": "Sting",
    "category": "Inne",
    "description": "",
    "icon": ""
  },
  {
    "name": "Mercurial",
    "category": "Inne",
    "description": "",
    "icon": ""
  },
  {
    "name": "Molten Drag on",
    "category": "Inne",
    "description": "",
    "icon": ""
  },
  {
    "name": "Mouldy",
    "category": "Inne",
    "description": "",
    "icon": ""
  },
  {
    "name": "Mummified",
    "category": "Inne",
    "description": "",
    "icon": ""
  },
  {
    "name": "Mutated Bat",
    "category": "Inne",
    "description": "",
    "icon": ""
  },
  {
    "name": "Mutated Rat",
    "category": "Inne",
    "description": "",
    "icon": ""
  },
  {
    "name": "Naga Archer",
    "category": "Inne",
    "description": "",
    "icon": ""
  },
  {
    "name": "Naga Warrior",
    "category": "Inne",
    "description": "",
    "icon": ""
  },
  {
    "name": "Night Harpy",
    "category": "Inne",
    "description": "",
    "icon": ""
  },
  {
    "name": "Nighthunter",
    "category": "Inne",
    "description": "",
    "icon": ""
  },
  {
    "name": "Nimmersatt's",
    "category": "Inne",
    "description": "",
    "icon": ""
  },
  {
    "name": "Shaman",
    "category": "Inne",
    "description": "",
    "icon": ""
  },
  {
    "name": "Old Girtablilu",
    "category": "Inne",
    "description": "",
    "icon": ""
  },
  {
    "name": "Orcish",
    "category": "Inne",
    "description": "",
    "icon": ""
  },
  {
    "name": "Ornate",
    "category": "Inne",
    "description": "",
    "icon": ""
  },
  {
    "name": "Pair of",
    "category": "Inne",
    "description": "",
    "icon": ""
  },
  {
    "name": "Hellflayer",
    "category": "Inne",
    "description": "",
    "icon": ""
  },
  {
    "name": "Piece of",
    "category": "Inne",
    "description": "",
    "icon": ""
  },
  {
    "name": "Drac onian",
    "category": "Inne",
    "description": "",
    "icon": ""
  },
  {
    "name": "Piece of Hell",
    "category": "Inne",
    "description": "",
    "icon": ""
  },
  {
    "name": "Souldespoiler",
    "category": "Inne",
    "description": "",
    "icon": ""
  },
  {
    "name": "Plasmatic",
    "category": "Inne",
    "description": "",
    "icon": ""
  },
  {
    "name": "Pool of",
    "category": "Inne",
    "description": "",
    "icon": ""
  },
  {
    "name": "Pot of Orcish",
    "category": "Inne",
    "description": "",
    "icon": ""
  },
  {
    "name": "Prehemoth",
    "category": "Inne",
    "description": "",
    "icon": ""
  },
  {
    "name": "Pressed",
    "category": "Inne",
    "description": "",
    "icon": ""
  },
  {
    "name": "Quara",
    "category": "Inne",
    "description": "",
    "icon": ""
  },
  {
    "name": "Red Goanna",
    "category": "Inne",
    "description": "",
    "icon": ""
  },
  {
    "name": "Resinous Fish",
    "category": "Inne",
    "description": "",
    "icon": ""
  },
  {
    "name": "Rhindeer",
    "category": "Inne",
    "description": "",
    "icon": ""
  },
  {
    "name": "Ritual Bone",
    "category": "Inne",
    "description": "",
    "icon": ""
  },
  {
    "name": "Rotten Piece",
    "category": "Inne",
    "description": "",
    "icon": ""
  },
  {
    "name": "Sandcrawler",
    "category": "Inne",
    "description": "",
    "icon": ""
  },
  {
    "name": "Scale of",
    "category": "Inne",
    "description": "",
    "icon": ""
  },
  {
    "name": "Scorpion",
    "category": "Inne",
    "description": "",
    "icon": ""
  },
  {
    "name": "Scroll of",
    "category": "Inne",
    "description": "",
    "icon": ""
  },
  {
    "name": "Shamanic",
    "category": "Inne",
    "description": "",
    "icon": ""
  },
  {
    "name": "Shimmering",
    "category": "Inne",
    "description": "",
    "icon": ""
  },
  {
    "name": "Shatterer",
    "category": "Inne",
    "description": "",
    "icon": ""
  },
  {
    "name": "Silencer",
    "category": "Inne",
    "description": "",
    "icon": ""
  },
  {
    "name": "Resonating",
    "category": "Inne",
    "description": "",
    "icon": ""
  },
  {
    "name": "Silken",
    "category": "Inne",
    "description": "",
    "icon": ""
  },
  {
    "name": "Silver Moon",
    "category": "Inne",
    "description": "",
    "icon": ""
  },
  {
    "name": "Single Human",
    "category": "Inne",
    "description": "",
    "icon": ""
  },
  {
    "name": "Skullcracker",
    "category": "Inne",
    "description": "",
    "icon": ""
  },
  {
    "name": "Slimy Leaf",
    "category": "Inne",
    "description": "",
    "icon": ""
  },
  {
    "name": "Small Flask of",
    "category": "Inne",
    "description": "",
    "icon": ""
  },
  {
    "name": "Small",
    "category": "Inne",
    "description": "",
    "icon": ""
  },
  {
    "name": "Small Treasure",
    "category": "Inne",
    "description": "",
    "icon": ""
  },
  {
    "name": "Small Tropical",
    "category": "Inne",
    "description": "",
    "icon": ""
  },
  {
    "name": "Sparkion",
    "category": "Inne",
    "description": "",
    "icon": ""
  },
  {
    "name": "Spellbook of",
    "category": "Inne",
    "description": "",
    "icon": ""
  },
  {
    "name": "Spellsinger's",
    "category": "Inne",
    "description": "",
    "icon": ""
  },
  {
    "name": "Spellweaver's",
    "category": "Inne",
    "description": "",
    "icon": ""
  },
  {
    "name": "Spiked Iron",
    "category": "Inne",
    "description": "",
    "icon": ""
  },
  {
    "name": "Stag",
    "category": "Inne",
    "description": "",
    "icon": ""
  },
  {
    "name": "Stampor",
    "category": "Inne",
    "description": "",
    "icon": ""
  },
  {
    "name": "Stonerefiner's",
    "category": "Inne",
    "description": "",
    "icon": ""
  },
  {
    "name": "Strange",
    "category": "Inne",
    "description": "",
    "icon": ""
  },
  {
    "name": "Streaked",
    "category": "Inne",
    "description": "",
    "icon": ""
  },
  {
    "name": "Sulphider",
    "category": "Inne",
    "description": "",
    "icon": ""
  },
  {
    "name": "Sulphur",
    "category": "Inne",
    "description": "",
    "icon": ""
  },
  {
    "name": "Sulphurous",
    "category": "Inne",
    "description": "",
    "icon": ""
  },
  {
    "name": "Swampling",
    "category": "Inne",
    "description": "",
    "icon": ""
  },
  {
    "name": "Swarmer",
    "category": "Inne",
    "description": "",
    "icon": ""
  },
  {
    "name": "Tail of",
    "category": "Inne",
    "description": "",
    "icon": ""
  },
  {
    "name": "Terramite",
    "category": "Inne",
    "description": "",
    "icon": ""
  },
  {
    "name": "Trapped Bad",
    "category": "Inne",
    "description": "",
    "icon": ""
  },
  {
    "name": "Tunnel Tyrant",
    "category": "Inne",
    "description": "",
    "icon": ""
  },
  {
    "name": "Two-Headed",
    "category": "Inne",
    "description": "",
    "icon": ""
  },
  {
    "name": "Undertaker",
    "category": "Inne",
    "description": "",
    "icon": ""
  },
  {
    "name": "Vampire's",
    "category": "Inne",
    "description": "",
    "icon": ""
  },
  {
    "name": "Volatile Proto",
    "category": "Inne",
    "description": "",
    "icon": ""
  },
  {
    "name": "Wardragon",
    "category": "Inne",
    "description": "",
    "icon": ""
  },
  {
    "name": "Weaver's",
    "category": "Inne",
    "description": "",
    "icon": ""
  },
  {
    "name": "Werebadger",
    "category": "Inne",
    "description": "",
    "icon": ""
  },
  {
    "name": "Werebear",
    "category": "Inne",
    "description": "",
    "icon": ""
  },
  {
    "name": "Wereboar",
    "category": "Inne",
    "description": "",
    "icon": ""
  },
  {
    "name": "Werecrocodile",
    "category": "Inne",
    "description": "",
    "icon": ""
  },
  {
    "name": "Werehyaena",
    "category": "Inne",
    "description": "",
    "icon": ""
  },
  {
    "name": "Werepanther",
    "category": "Inne",
    "description": "",
    "icon": ""
  },
  {
    "name": "Weretiger",
    "category": "Inne",
    "description": "",
    "icon": ""
  },
  {
    "name": "Widow's",
    "category": "Inne",
    "description": "",
    "icon": ""
  },
  {
    "name": "Wimp Tooth",
    "category": "Inne",
    "description": "",
    "icon": ""
  },
  {
    "name": "Wooden",
    "category": "Inne",
    "description": "",
    "icon": ""
  },
  {
    "name": "Yapunac",
    "category": "Inne",
    "description": "",
    "icon": ""
  },
  {
    "name": "Ruin",
    "category": "Inne",
    "description": "",
    "icon": ""
  },
  {
    "name": "Zaogun",
    "category": "Inne",
    "description": "",
    "icon": ""
  }
]